{
  "images": [
    {
      "title": "River Khwae",
      "year": "2016-07-19T00:00:00.000Z",
      "category": "sketch",
      "srcImage": "https://www.datocms-assets.com/159/1482185522-201603_RiverKhwae_small.jpg?fm=jpg&w=400",
      "mobileImage": {
        "src": "https://www.datocms-assets.com/159/1482185522-201603_RiverKhwae_small.jpg?fm=jpg&w=800",
        "width": 800,
        "height": 553
      },
      "desktopImage": {
        "src": "https://www.datocms-assets.com/159/1482185522-201603_RiverKhwae_small.jpg?fm=jpg&w=2000",
        "width": 2000,
        "height": 1383
      },
      "description": "Ink sketch",
      "alt": "River Khwae sketch by V Chan",
      "showInPortfolio": false
    },
    {
      "title": "Death Cab for Cutie poster",
      "year": "2016-05-16T00:00:00.000Z",
      "category": "commercial",
      "srcImage": "https://www.datocms-assets.com/159/1482185625-201603_Deathcab.jpg?fm=jpg&w=400",
      "mobileImage": {
        "src": "https://www.datocms-assets.com/159/1482185625-201603_Deathcab.jpg?fm=jpg&w=800",
        "width": 800,
        "height": 1135
      },
      "desktopImage": {
        "src": "https://www.datocms-assets.com/159/1482185625-201603_Deathcab.jpg?fm=jpg&w=2000",
        "width": 2000,
        "height": 2838
      },
      "description": "Commercial graphic design",
      "alt": "Death Cab for Cutie poster by Vickie Chan",
      "showInPortfolio": false
    },
    {
      "title": "Surviving Hong Kong Series: Opening a Pack of Calbees",
      "year": "2016-10-11T00:00:00.000Z",
      "category": "illustration",
      "srcImage": "https://www.datocms-assets.com/159/1482185704-15SurvHK20160223Calbees.jpg?fm=jpg&w=400",
      "mobileImage": {
        "src": "https://www.datocms-assets.com/159/1482185704-15SurvHK20160223Calbees.jpg?fm=jpg&w=800",
        "width": 800,
        "height": 1010
      },
      "desktopImage": {
        "src": "https://www.datocms-assets.com/159/1482185704-15SurvHK20160223Calbees.jpg?fm=jpg&w=2000",
        "width": 2000,
        "height": 2525
      },
      "description": "Illustration",
      "alt": "Surviving Hong Kong: Opening a Pack of Calbees illustration by Vickie Chan",
      "showInPortfolio": false
    },
    {
      "title": "Surviving Hong Kong Series: Lift Etiquette",
      "year": "2016-10-10T00:00:00.000Z",
      "category": "illustration",
      "srcImage": "https://www.datocms-assets.com/159/1482185787-14SurvHK20160218Lift.jpg?fm=jpg&w=400",
      "mobileImage": {
        "src": "https://www.datocms-assets.com/159/1482185787-14SurvHK20160218Lift.jpg?fm=jpg&w=800",
        "width": 800,
        "height": 1025
      },
      "desktopImage": {
        "src": "https://www.datocms-assets.com/159/1482185787-14SurvHK20160218Lift.jpg?fm=jpg&w=2000",
        "width": 2000,
        "height": 2564
      },
      "description": "Illustration",
      "alt": "Surviving Hong Kong: Lift Etiquette illustration by Vickie Chan",
      "showInPortfolio": false
    },
    {
      "title": "Surviving Hong Kong Series: Cinema-going",
      "year": "2016-02-17T00:00:00.000Z",
      "category": " illustration",
      "srcImage": "https://www.datocms-assets.com/159/1483119156-13survhk20160214cinema-jpg?fm=jpg&w=400",
      "mobileImage": {
        "src": "https://www.datocms-assets.com/159/1483119156-13survhk20160214cinema-jpg?fm=jpg&w=800",
        "width": 800,
        "height": 1047
      },
      "desktopImage": {
        "src": "https://www.datocms-assets.com/159/1483119156-13survhk20160214cinema-jpg?fm=jpg&w=2000",
        "width": 2000,
        "height": 2618
      },
      "description": "Illustration",
      "alt": "Surviving Hong Kong: Cinema-going illustration by Vickie Chan",
      "showInPortfolio": false
    },
    {
      "title": "Year of the Monkey Lai See (利是) envelopes",
      "year": "2016-01-01T00:00:00.000Z",
      "category": "illustration screenprint",
      "srcImage": "https://www.datocms-assets.com/159/1483119654-201601cnylaiseeall-jpg?fm=jpg&w=400",
      "mobileImage": {
        "src": "https://www.datocms-assets.com/159/1483119654-201601cnylaiseeall-jpg?fm=jpg&w=800",
        "width": 800,
        "height": 725
      },
      "desktopImage": {
        "src": "https://www.datocms-assets.com/159/1483119654-201601cnylaiseeall-jpg?fm=jpg&w=2000",
        "width": 2000,
        "height": 1812
      },
      "description": "Screenprint of illustration",
      "alt": "Chinese New Year lai see envelopes illustrated and screenprinted by Vickie Chan",
      "showInPortfolio": true
    },
    {
      "title": "Surviving Hong Kong: Toilets",
      "year": "2016-02-16T00:00:00.000Z",
      "category": "Illustration",
      "srcImage": "https://www.datocms-assets.com/159/1483120156-12survhk2016012toilets-jpg?fm=jpg&w=400",
      "mobileImage": {
        "src": "https://www.datocms-assets.com/159/1483120156-12survhk2016012toilets-jpg?fm=jpg&w=800",
        "width": 800,
        "height": 1089
      },
      "desktopImage": {
        "src": "https://www.datocms-assets.com/159/1483120156-12survhk2016012toilets-jpg?fm=jpg&w=2000",
        "width": 2000,
        "height": 2723
      },
      "description": "Illustration",
      "alt": "Surviving Hong Kong: Toilets illustration by Vickie Chan",
      "showInPortfolio": false
    },
    {
      "title": "Surviving Hong Kong: Got Milk?",
      "year": "2015-11-17T00:00:00.000Z",
      "category": "Illustration",
      "srcImage": "https://www.datocms-assets.com/159/1483120659-11survhk201512gotmilk-jpg?fm=jpg&w=400",
      "mobileImage": {
        "src": "https://www.datocms-assets.com/159/1483120659-11survhk201512gotmilk-jpg?fm=jpg&w=800",
        "width": 800,
        "height": 1076
      },
      "desktopImage": {
        "src": "https://www.datocms-assets.com/159/1483120659-11survhk201512gotmilk-jpg?fm=jpg&w=2000",
        "width": 2000,
        "height": 2690
      },
      "description": "Illustration",
      "alt": "Surviving Hong Kong: Got Milk? illustration by Vickie Chan",
      "showInPortfolio": false
    },
    {
      "title": "Surviving Hong Kong Series: Water Dispenser",
      "year": "2015-09-23T00:00:00.000Z",
      "category": "illustration",
      "srcImage": "https://www.datocms-assets.com/159/1506164862-10survhk201512waterhotsmall.jpg?fm=jpg&w=400",
      "mobileImage": {
        "src": "https://www.datocms-assets.com/159/1506164862-10survhk201512waterhotsmall.jpg?fm=jpg&w=800",
        "width": 800,
        "height": 1066
      },
      "desktopImage": {
        "src": "https://www.datocms-assets.com/159/1506164862-10survhk201512waterhotsmall.jpg?fm=jpg&w=2000",
        "width": 2000,
        "height": 2667
      },
      "description": "Illustration",
      "alt": "Surviving Hong Kong: Water Dispenser illustration by Vickie Chan",
      "showInPortfolio": false
    },
    {
      "title": "Surviving Hong Kong Series: Clockenflap",
      "year": "2015-09-23T00:00:00.000Z",
      "category": "illustration",
      "srcImage": "https://www.datocms-assets.com/159/1506165051-9survhk201511clknflp.jpg?fm=jpg&w=400",
      "mobileImage": {
        "src": "https://www.datocms-assets.com/159/1506165051-9survhk201511clknflp.jpg?fm=jpg&w=800",
        "width": 800,
        "height": 1142
      },
      "desktopImage": {
        "src": "https://www.datocms-assets.com/159/1506165051-9survhk201511clknflp.jpg?fm=jpg&w=2000",
        "width": 2000,
        "height": 2857
      },
      "description": "Illustration",
      "alt": "Surviving Hong Kong: Clockenflap illustration by Vickie Chan",
      "showInPortfolio": false
    },
    {
      "title": "Surviving Hong Kong Series: Wearing a Mask",
      "year": "2015-09-23T00:00:00.000Z",
      "category": "illustration",
      "srcImage": "https://www.datocms-assets.com/159/1506168216-8survhk201511masks.jpg?fm=jpg&w=400",
      "mobileImage": {
        "src": "https://www.datocms-assets.com/159/1506168216-8survhk201511masks.jpg?fm=jpg&w=800",
        "width": 800,
        "height": 1219
      },
      "desktopImage": {
        "src": "https://www.datocms-assets.com/159/1506168216-8survhk201511masks.jpg?fm=jpg&w=2000",
        "width": 2000,
        "height": 3048
      },
      "description": "Illustration",
      "alt": "Surviving Hong Kong: Wearing a Mask illustration by Vickie Chan",
      "showInPortfolio": false
    },
    {
      "title": "Surviving Hong Kong Series: No Fitting",
      "year": "2015-09-23T00:00:00.000Z",
      "category": "illustration",
      "srcImage": "https://www.datocms-assets.com/159/1506168319-7survhk201511nofitting.jpg?fm=jpg&w=400",
      "mobileImage": {
        "src": "https://www.datocms-assets.com/159/1506168319-7survhk201511nofitting.jpg?fm=jpg&w=800",
        "width": 800,
        "height": 1165
      },
      "desktopImage": {
        "src": "https://www.datocms-assets.com/159/1506168319-7survhk201511nofitting.jpg?fm=jpg&w=2000",
        "width": 2000,
        "height": 2913
      },
      "description": "Illustration",
      "alt": "Surviving Hong Kong: No Fitting illustration by Vickie Chan",
      "showInPortfolio": false
    },
    {
      "title": "Surviving Hong Kong Series: Escalators",
      "year": "2015-09-23T00:00:00.000Z",
      "category": "illustration",
      "srcImage": "https://www.datocms-assets.com/159/1506170160-4survhk201508escalators.jpg?fm=jpg&w=400",
      "mobileImage": {
        "src": "https://www.datocms-assets.com/159/1506170160-4survhk201508escalators.jpg?fm=jpg&w=800",
        "width": 800,
        "height": 1049
      },
      "desktopImage": {
        "src": "https://www.datocms-assets.com/159/1506170160-4survhk201508escalators.jpg?fm=jpg&w=2000",
        "width": 2000,
        "height": 2623
      },
      "description": "Illustration",
      "alt": "Surviving Hong Kong: Escalators illustration by Vickie Chan",
      "showInPortfolio": false
    },
    {
      "title": "Surviving Hong Kong Series: Railings",
      "year": "2015-09-01T00:00:00.000Z",
      "category": "illustration",
      "srcImage": "https://www.datocms-assets.com/159/1506170230-1survhk201508railings.jpg?fm=jpg&w=400",
      "mobileImage": {
        "src": "https://www.datocms-assets.com/159/1506170230-1survhk201508railings.jpg?fm=jpg&w=800",
        "width": 800,
        "height": 902
      },
      "desktopImage": {
        "src": "https://www.datocms-assets.com/159/1506170230-1survhk201508railings.jpg?fm=jpg&w=2000",
        "width": 2000,
        "height": 2255
      },
      "description": "Illustration",
      "alt": "Surviving Hong Kong: Railings illustration by Vickie Chan",
      "showInPortfolio": true
    },
    {
      "title": "Surviving Hong Kong Series: Walking",
      "year": "2015-09-01T00:00:00.000Z",
      "category": "illustration",
      "srcImage": "https://www.datocms-assets.com/159/1506170296-5survhk201510walking.jpg?fm=jpg&w=400",
      "mobileImage": {
        "src": "https://www.datocms-assets.com/159/1506170296-5survhk201510walking.jpg?fm=jpg&w=800",
        "width": 800,
        "height": 1119
      },
      "desktopImage": {
        "src": "https://www.datocms-assets.com/159/1506170296-5survhk201510walking.jpg?fm=jpg&w=2000",
        "width": 2000,
        "height": 2797
      },
      "description": "Illustration",
      "alt": "Surviving Hong Kong Series: Walking illustration by Vickie Chan",
      "showInPortfolio": false
    },
    {
      "title": "Surviving Hong Kong Series: Peripheral Vision",
      "year": "2015-09-23T00:00:00.000Z",
      "category": "illustration",
      "srcImage": "https://www.datocms-assets.com/159/1506170376-3survhk201508peripheralvision.jpg?fm=jpg&w=400",
      "mobileImage": {
        "src": "https://www.datocms-assets.com/159/1506170376-3survhk201508peripheralvision.jpg?fm=jpg&w=800",
        "width": 800,
        "height": 1048
      },
      "desktopImage": {
        "src": "https://www.datocms-assets.com/159/1506170376-3survhk201508peripheralvision.jpg?fm=jpg&w=2000",
        "width": 2000,
        "height": 2621
      },
      "description": "illlustration",
      "alt": "Surviving Hong Kong Series: Peripheral Vision illustration by Vickie Chan",
      "showInPortfolio": false
    },
    {
      "title": "The Days Run Away (illustration)",
      "year": "2017-09-20T00:00:00.000Z",
      "category": "illustration",
      "srcImage": "https://www.datocms-assets.com/159/1506170530-201506_thedaysrunaway.jpg?fm=jpg&w=400",
      "mobileImage": {
        "src": "https://www.datocms-assets.com/159/1506170530-201506_thedaysrunaway.jpg?fm=jpg&w=800",
        "width": 800,
        "height": 699
      },
      "desktopImage": {
        "src": "https://www.datocms-assets.com/159/1506170530-201506_thedaysrunaway.jpg?fm=jpg&w=2000",
        "width": 2000,
        "height": 1748
      },
      "description": "Illustration",
      "alt": "The Days Run Away illustration by Vickie Chan",
      "showInPortfolio": false
    },
    {
      "title": "Angkor Wat Overprint",
      "year": "2015-09-01T00:00:00.000Z",
      "category": "illustration commercial mixed-media screenprint",
      "srcImage": "https://www.datocms-assets.com/159/1506170602-201501_angkorwatfullbgrblueyellowoverprint.jpg?fm=jpg&w=400",
      "mobileImage": {
        "src": "https://www.datocms-assets.com/159/1506170602-201501_angkorwatfullbgrblueyellowoverprint.jpg?fm=jpg&w=800",
        "width": 800,
        "height": 587
      },
      "desktopImage": {
        "src": "https://www.datocms-assets.com/159/1506170602-201501_angkorwatfullbgrblueyellowoverprint.jpg?fm=jpg&w=2000",
        "width": 2000,
        "height": 1469
      },
      "description": "Screenprint on mixed media background",
      "alt": "Angkor Wat screenprint by Vickie Chan",
      "showInPortfolio": true
    },
    {
      "title": "Existentialism on Prom Night",
      "year": "2015-09-01T00:00:00.000Z",
      "category": "painting mixed-media",
      "srcImage": "https://www.datocms-assets.com/159/1506170683-2015_existentialismonpromnight_20.jpg?fm=jpg&w=400",
      "mobileImage": {
        "src": "https://www.datocms-assets.com/159/1506170683-2015_existentialismonpromnight_20.jpg?fm=jpg&w=800",
        "width": 800,
        "height": 800
      },
      "desktopImage": {
        "src": "https://www.datocms-assets.com/159/1506170683-2015_existentialismonpromnight_20.jpg?fm=jpg&w=2000",
        "width": 2000,
        "height": 2000
      },
      "description": "Mixed media on canvas",
      "alt": "Existentialism on Prom Night mixed media painting on canvas by Vickie Chan",
      "showInPortfolio": false
    },
    {
      "title": "But You'll Cry",
      "year": "2015-04-30T00:00:00.000Z",
      "category": "mixed-media painting",
      "srcImage": "https://www.datocms-assets.com/159/1480881962-ButYoullCry-FULL.jpg?fm=jpg&w=400",
      "mobileImage": {
        "src": "https://www.datocms-assets.com/159/1480881962-ButYoullCry-FULL.jpg?fm=jpg&w=800",
        "width": 800,
        "height": 1097
      },
      "desktopImage": {
        "src": "https://www.datocms-assets.com/159/1480881962-ButYoullCry-FULL.jpg?fm=jpg&w=2000",
        "width": 2000,
        "height": 2743
      },
      "description": "Mixed media painting on vinyl record ",
      "alt": "But You'll Cry vinyl painting by Vickie Chan",
      "showInPortfolio": true
    },
    {
      "title": "Other People's Heartache",
      "year": "2015-09-16T00:00:00.000Z",
      "category": "mixed-media painting",
      "srcImage": "https://www.datocms-assets.com/159/1506171539-otherpeoplesheartache-full.jpg?fm=jpg&w=400",
      "mobileImage": {
        "src": "https://www.datocms-assets.com/159/1506171539-otherpeoplesheartache-full.jpg?fm=jpg&w=800",
        "width": 800,
        "height": 1098
      },
      "desktopImage": {
        "src": "https://www.datocms-assets.com/159/1506171539-otherpeoplesheartache-full.jpg?fm=jpg&w=2000",
        "width": 2000,
        "height": 2746
      },
      "description": "Mixed media painting on vinyl record",
      "alt": "Other People's Heartache vinyl painting by Vickie Chan",
      "showInPortfolio": false
    },
    {
      "title": "Michael's Bear Trap",
      "year": "2015-09-15T00:00:00.000Z",
      "category": "illustration",
      "srcImage": "https://www.datocms-assets.com/159/1506171613-michaelsbeartrap.jpg?fm=jpg&w=400",
      "mobileImage": {
        "src": "https://www.datocms-assets.com/159/1506171613-michaelsbeartrap.jpg?fm=jpg&w=800",
        "width": 800,
        "height": 530
      },
      "desktopImage": {
        "src": "https://www.datocms-assets.com/159/1506171613-michaelsbeartrap.jpg?fm=jpg&w=2000",
        "width": 2000,
        "height": 1327
      },
      "description": "Ink illustration",
      "alt": "Michael's Bear Trap illustration by Vickie Chan",
      "showInPortfolio": false
    },
    {
      "title": "Dozer screenprint (pink)",
      "year": "2015-09-23T00:00:00.000Z",
      "category": "screenprint commercial illustration",
      "srcImage": "https://www.datocms-assets.com/159/1506171706-201510_dozerpinkbrown.jpg?fm=jpg&w=400",
      "mobileImage": {
        "src": "https://www.datocms-assets.com/159/1506171706-201510_dozerpinkbrown.jpg?fm=jpg&w=800",
        "width": 800,
        "height": 576
      },
      "desktopImage": {
        "src": "https://www.datocms-assets.com/159/1506171706-201510_dozerpinkbrown.jpg?fm=jpg&w=2000",
        "width": 2000,
        "height": 1441
      },
      "description": "Embellished screenprint",
      "alt": "Dozer embellished screenprint by Vickie Chan",
      "showInPortfolio": false
    },
    {
      "title": "Dozer screenprint with forest (green)",
      "year": "2015-09-23T00:00:00.000Z",
      "category": "screenprint mixed-media commercial illustration",
      "srcImage": "https://www.datocms-assets.com/159/1506171767-201510_dbt6-8deerpatbgrgreen-dkgreydog_small.jpg?fm=jpg&w=400",
      "mobileImage": {
        "src": "https://www.datocms-assets.com/159/1506171767-201510_dbt6-8deerpatbgrgreen-dkgreydog_small.jpg?fm=jpg&w=800",
        "width": 800,
        "height": 587
      },
      "desktopImage": {
        "src": "https://www.datocms-assets.com/159/1506171767-201510_dbt6-8deerpatbgrgreen-dkgreydog_small.jpg?fm=jpg&w=2000",
        "width": 2000,
        "height": 1469
      },
      "description": "Embellished screenprint",
      "alt": "Dozer and forest screenprint by Vickie Chan",
      "showInPortfolio": false
    },
    {
      "title": "Leicester Fox",
      "year": "2015-09-01T00:00:00.000Z",
      "category": "illustration",
      "srcImage": "https://www.datocms-assets.com/159/1506171823-leicesterfoxclean.jpg?fm=jpg&w=400",
      "mobileImage": {
        "src": "https://www.datocms-assets.com/159/1506171823-leicesterfoxclean.jpg?fm=jpg&w=800",
        "width": 800,
        "height": 556
      },
      "desktopImage": {
        "src": "https://www.datocms-assets.com/159/1506171823-leicesterfoxclean.jpg?fm=jpg&w=2000",
        "width": 2000,
        "height": 1391
      },
      "description": "Ink Illustration",
      "alt": "Leicester Fox illustration by Vickie Chan",
      "showInPortfolio": true
    },
    {
      "title": "Olly & Rachel",
      "year": "2015-09-01T00:00:00.000Z",
      "category": "commercial",
      "srcImage": "https://www.datocms-assets.com/159/1506171903-2015_ollyweddinginvite_ol.jpg?fm=jpg&w=400",
      "mobileImage": {
        "src": "https://www.datocms-assets.com/159/1506171903-2015_ollyweddinginvite_ol.jpg?fm=jpg&w=800",
        "width": 800,
        "height": 829
      },
      "desktopImage": {
        "src": "https://www.datocms-assets.com/159/1506171903-2015_ollyweddinginvite_ol.jpg?fm=jpg&w=2000",
        "width": 2000,
        "height": 2074
      },
      "description": "Wedding card",
      "alt": "Wedding invitations (Olly & Rachel) by Vickie Chan",
      "showInPortfolio": false
    },
    {
      "title": "Sunshine Map",
      "year": "2014-09-23T00:00:00.000Z",
      "category": "commercial",
      "srcImage": "https://www.datocms-assets.com/159/1506171962-201410_egyptsunshinemap.jpg?fm=jpg&w=400",
      "mobileImage": {
        "src": "https://www.datocms-assets.com/159/1506171962-201410_egyptsunshinemap.jpg?fm=jpg&w=800",
        "width": 800,
        "height": 378
      },
      "desktopImage": {
        "src": "https://www.datocms-assets.com/159/1506171962-201410_egyptsunshinemap.jpg?fm=jpg&w=2000",
        "width": 2000,
        "height": 947
      },
      "description": "Sunshine Map",
      "alt": "Sunshine map graphic by Vickie Chan",
      "showInPortfolio": false
    },
    {
      "title": "Ta Phrom (pink)",
      "year": "2014-09-23T00:00:00.000Z",
      "category": "screenprint commerical illustration",
      "srcImage": "https://www.datocms-assets.com/159/1506172030-2014_tp2-10pink_201412.jpg?fm=jpg&w=400",
      "mobileImage": {
        "src": "https://www.datocms-assets.com/159/1506172030-2014_tp2-10pink_201412.jpg?fm=jpg&w=800",
        "width": 800,
        "height": 581
      },
      "desktopImage": {
        "src": "https://www.datocms-assets.com/159/1506172030-2014_tp2-10pink_201412.jpg?fm=jpg&w=2000",
        "width": 2000,
        "height": 1453
      },
      "description": "Screenprint",
      "alt": "Ta Phrom (pink) screenprint by Vickie Chan",
      "showInPortfolio": false
    },
    {
      "title": "Angkor Wat, East Gate (orange, drawn over)",
      "year": "2014-09-09T00:00:00.000Z",
      "category": "screenprint mixed-media commercial illustration",
      "srcImage": "https://www.datocms-assets.com/159/1506172176-aw5-10_angkorwateastgateorangedraw-201408.jpg?fm=jpg&w=400",
      "mobileImage": {
        "src": "https://www.datocms-assets.com/159/1506172176-aw5-10_angkorwateastgateorangedraw-201408.jpg?fm=jpg&w=800",
        "width": 800,
        "height": 531
      },
      "desktopImage": {
        "src": "https://www.datocms-assets.com/159/1506172176-aw5-10_angkorwateastgateorangedraw-201408.jpg?fm=jpg&w=2000",
        "width": 2000,
        "height": 1328
      },
      "description": "screenprint",
      "alt": "Angkor Wat, East Gate (orange, drawn over) screenprint by Vickie Chan",
      "showInPortfolio": false
    },
    {
      "title": "Angkor Wat, East Gate (brown and yellow)",
      "year": "2014-09-23T00:00:00.000Z",
      "category": "screenprint commercial illustration",
      "srcImage": "https://www.datocms-assets.com/159/1506172238-aw4-10_eastgatebrownyelloverprint-201406.jpg?fm=jpg&w=400",
      "mobileImage": {
        "src": "https://www.datocms-assets.com/159/1506172238-aw4-10_eastgatebrownyelloverprint-201406.jpg?fm=jpg&w=800",
        "width": 800,
        "height": 531
      },
      "desktopImage": {
        "src": "https://www.datocms-assets.com/159/1506172238-aw4-10_eastgatebrownyelloverprint-201406.jpg?fm=jpg&w=2000",
        "width": 2000,
        "height": 1328
      },
      "description": "Screenprint",
      "alt": "Angkor Wat, East Gate (brown and yellow) screenprint by Vickie Chan",
      "showInPortfolio": false
    },
    {
      "title": "Beggar in the Morning",
      "year": "2014-09-10T00:00:00.000Z",
      "category": "painting mixed-media",
      "srcImage": "https://www.datocms-assets.com/159/1506172295-beggarinthemorning_30_small.jpg?fm=jpg&w=400",
      "mobileImage": {
        "src": "https://www.datocms-assets.com/159/1506172295-beggarinthemorning_30_small.jpg?fm=jpg&w=800",
        "width": 800,
        "height": 796
      },
      "desktopImage": {
        "src": "https://www.datocms-assets.com/159/1506172295-beggarinthemorning_30_small.jpg?fm=jpg&w=2000",
        "width": 2000,
        "height": 1991
      },
      "description": "Mixed media on canvas",
      "alt": "Beggar in the Morning painting by Vickie Chan",
      "showInPortfolio": false
    },
    {
      "title": "Ta Phrom",
      "year": "2014-09-17T00:00:00.000Z",
      "category": "sketch",
      "srcImage": "https://www.datocms-assets.com/159/1506172355-taphrom.jpg?fm=jpg&w=400",
      "mobileImage": {
        "src": "https://www.datocms-assets.com/159/1506172355-taphrom.jpg?fm=jpg&w=800",
        "width": 800,
        "height": 542
      },
      "desktopImage": {
        "src": "https://www.datocms-assets.com/159/1506172355-taphrom.jpg?fm=jpg&w=2000",
        "width": 2000,
        "height": 1355
      },
      "description": "Ink sketch",
      "alt": "Ta Phrom sketch by Vickie Chan",
      "showInPortfolio": false
    },
    {
      "title": "Angkor Wat, East Gate",
      "year": "2014-09-17T00:00:00.000Z",
      "category": "sketch",
      "srcImage": "https://www.datocms-assets.com/159/1506172446-angkoreastgate.jpg?fm=jpg&w=400",
      "mobileImage": {
        "src": "https://www.datocms-assets.com/159/1506172446-angkoreastgate.jpg?fm=jpg&w=800",
        "width": 800,
        "height": 527
      },
      "desktopImage": {
        "src": "https://www.datocms-assets.com/159/1506172446-angkoreastgate.jpg?fm=jpg&w=2000",
        "width": 2000,
        "height": 1317
      },
      "description": "Ink sketch",
      "alt": "Angkor Wat, East Gate sketch by Vickie Chan",
      "showInPortfolio": false
    },
    {
      "title": "Ta Phrom embellished screenprint",
      "year": "2014-09-23T00:00:00.000Z",
      "category": "mixed-media screenprint commercial illustration",
      "srcImage": "https://www.datocms-assets.com/159/1506172510-201412_tp3taphrompinkdrawover.jpg?fm=jpg&w=400",
      "mobileImage": {
        "src": "https://www.datocms-assets.com/159/1506172510-201412_tp3taphrompinkdrawover.jpg?fm=jpg&w=800",
        "width": 800,
        "height": 555
      },
      "desktopImage": {
        "src": "https://www.datocms-assets.com/159/1506172510-201412_tp3taphrompinkdrawover.jpg?fm=jpg&w=2000",
        "width": 2000,
        "height": 1389
      },
      "description": "Embellished screenprint",
      "alt": "Ta Phrom embellished screenprint by Vickie Chan",
      "showInPortfolio": false
    },
    {
      "title": "Folkestone Crescent",
      "year": "2013-09-10T00:00:00.000Z",
      "category": "sketch",
      "srcImage": "https://www.datocms-assets.com/159/1506172552-folkestonecrescent.jpg?fm=jpg&w=400",
      "mobileImage": {
        "src": "https://www.datocms-assets.com/159/1506172552-folkestonecrescent.jpg?fm=jpg&w=800",
        "width": 800,
        "height": 562
      },
      "desktopImage": {
        "src": "https://www.datocms-assets.com/159/1506172552-folkestonecrescent.jpg?fm=jpg&w=2000",
        "width": 2000,
        "height": 1407
      },
      "description": "Ink sketch",
      "alt": "Folkestone Crescent sketch by Vickie Chan",
      "showInPortfolio": false
    },
    {
      "title": "Third St (colour)",
      "year": "2013-09-17T00:00:00.000Z",
      "category": "sketch",
      "srcImage": "https://www.datocms-assets.com/159/1506172606-thirdstcolour.jpg?fm=jpg&w=400",
      "mobileImage": {
        "src": "https://www.datocms-assets.com/159/1506172606-thirdstcolour.jpg?fm=jpg&w=800",
        "width": 800,
        "height": 1153
      },
      "desktopImage": {
        "src": "https://www.datocms-assets.com/159/1506172606-thirdstcolour.jpg?fm=jpg&w=2000",
        "width": 2000,
        "height": 2883
      },
      "description": "Ink sketch",
      "alt": "Third St (colour) sketch by Vickie Chan",
      "showInPortfolio": false
    },
    {
      "title": "Rice Wine Bottle (colour)",
      "year": "2013-09-25T00:00:00.000Z",
      "category": "illustration",
      "srcImage": "https://www.datocms-assets.com/159/1506172662-ricewinebottlecolour.jpg?fm=jpg&w=400",
      "mobileImage": {
        "src": "https://www.datocms-assets.com/159/1506172662-ricewinebottlecolour.jpg?fm=jpg&w=800",
        "width": 800,
        "height": 1127
      },
      "desktopImage": {
        "src": "https://www.datocms-assets.com/159/1506172662-ricewinebottlecolour.jpg?fm=jpg&w=2000",
        "width": 2000,
        "height": 2818
      },
      "description": "Colour ink illustration",
      "alt": "Rice wine bottle ink illustration by Vickie Chan",
      "showInPortfolio": false
    },
    {
      "title": "Third St (black & white)",
      "year": "2013-09-18T00:00:00.000Z",
      "category": "sketch",
      "srcImage": "https://www.datocms-assets.com/159/1506172722-thirdst.jpg?fm=jpg&w=400",
      "mobileImage": {
        "src": "https://www.datocms-assets.com/159/1506172722-thirdst.jpg?fm=jpg&w=800",
        "width": 800,
        "height": 1129
      },
      "desktopImage": {
        "src": "https://www.datocms-assets.com/159/1506172722-thirdst.jpg?fm=jpg&w=2000",
        "width": 2000,
        "height": 2823
      },
      "description": "Ink sketch",
      "alt": "Third St ink sketch by Vickie Chan",
      "showInPortfolio": false
    },
    {
      "title": "Maple Syrup",
      "year": "2013-09-18T00:00:00.000Z",
      "category": "illustration",
      "srcImage": "https://www.datocms-assets.com/159/1506172772-maplesyrup.jpg?fm=jpg&w=400",
      "mobileImage": {
        "src": "https://www.datocms-assets.com/159/1506172772-maplesyrup.jpg?fm=jpg&w=800",
        "width": 800,
        "height": 1079
      },
      "desktopImage": {
        "src": "https://www.datocms-assets.com/159/1506172772-maplesyrup.jpg?fm=jpg&w=2000",
        "width": 2000,
        "height": 2699
      },
      "description": "Ink illustration",
      "alt": "Maple Syrup ink illustration by Vickie Chan",
      "showInPortfolio": false
    },
    {
      "title": "Rice Wine Bottle (black & white)",
      "year": "2013-09-18T00:00:00.000Z",
      "category": "illustration",
      "srcImage": "https://www.datocms-assets.com/159/1506172845-ricewinebottle.jpg?fm=jpg&w=400",
      "mobileImage": {
        "src": "https://www.datocms-assets.com/159/1506172845-ricewinebottle.jpg?fm=jpg&w=800",
        "width": 800,
        "height": 1202
      },
      "desktopImage": {
        "src": "https://www.datocms-assets.com/159/1506172845-ricewinebottle.jpg?fm=jpg&w=2000",
        "width": 2000,
        "height": 3006
      },
      "description": "Ink Illustration",
      "alt": "Rice wine bottle ink illustration by Vickie Chan",
      "showInPortfolio": false
    },
    {
      "title": "Hanalei",
      "year": "2012-09-18T00:00:00.000Z",
      "category": "sketch",
      "srcImage": "https://www.datocms-assets.com/159/1506173602-hanalei.jpg?fm=jpg&w=400",
      "mobileImage": {
        "src": "https://www.datocms-assets.com/159/1506173602-hanalei.jpg?fm=jpg&w=800",
        "width": 800,
        "height": 552
      },
      "desktopImage": {
        "src": "https://www.datocms-assets.com/159/1506173602-hanalei.jpg?fm=jpg&w=2000",
        "width": 2000,
        "height": 1380
      },
      "description": "Ink sketch",
      "alt": "Hanalei ink sketch by Vickie Chan",
      "showInPortfolio": false
    },
    {
      "title": "Folkestone Lighthouse",
      "year": "2012-09-18T00:00:00.000Z",
      "category": "sketch",
      "srcImage": "https://www.datocms-assets.com/159/1506173655-folkestonelight20.jpg?fm=jpg&w=400",
      "mobileImage": {
        "src": "https://www.datocms-assets.com/159/1506173655-folkestonelight20.jpg?fm=jpg&w=800",
        "width": 800,
        "height": 561
      },
      "desktopImage": {
        "src": "https://www.datocms-assets.com/159/1506173655-folkestonelight20.jpg?fm=jpg&w=2000",
        "width": 2000,
        "height": 1404
      },
      "description": "Ink sketch",
      "alt": "Folkestone Lighthouse ink sketch by Vickie Chan",
      "showInPortfolio": false
    },
    {
      "title": "Folkestone Bench",
      "year": "2012-09-27T00:00:00.000Z",
      "category": "sketch",
      "srcImage": "https://www.datocms-assets.com/159/1506173711-folkestonebench.jpg?fm=jpg&w=400",
      "mobileImage": {
        "src": "https://www.datocms-assets.com/159/1506173711-folkestonebench.jpg?fm=jpg&w=800",
        "width": 800,
        "height": 548
      },
      "desktopImage": {
        "src": "https://www.datocms-assets.com/159/1506173711-folkestonebench.jpg?fm=jpg&w=2000",
        "width": 2000,
        "height": 1370
      },
      "description": "Ink sketch",
      "alt": "Folkestone Bench ink sketch by Vickie Chan",
      "showInPortfolio": false
    },
    {
      "title": "Enoshima",
      "year": "2012-09-19T00:00:00.000Z",
      "category": "sketch",
      "srcImage": "https://www.datocms-assets.com/159/1506173762-enoshima.jpg?fm=jpg&w=400",
      "mobileImage": {
        "src": "https://www.datocms-assets.com/159/1506173762-enoshima.jpg?fm=jpg&w=800",
        "width": 800,
        "height": 1173
      },
      "desktopImage": {
        "src": "https://www.datocms-assets.com/159/1506173762-enoshima.jpg?fm=jpg&w=2000",
        "width": 2000,
        "height": 2933
      },
      "description": "Ink sketch",
      "alt": "Enoshima ink sketch by Vickie Chan",
      "showInPortfolio": false
    },
    {
      "title": "68 Bus web banner",
      "year": "2011-09-16T00:00:00.000Z",
      "category": "Commercial illustration",
      "srcImage": "https://www.datocms-assets.com/159/1506173943-2011_7_68miraradiomovingwebbanner.jpg?fm=jpg&w=400",
      "mobileImage": {
        "src": "https://www.datocms-assets.com/159/1506173943-2011_7_68miraradiomovingwebbanner.jpg?fm=jpg&w=800",
        "width": 800,
        "height": 153
      },
      "desktopImage": {
        "src": "https://www.datocms-assets.com/159/1506173943-2011_7_68miraradiomovingwebbanner.jpg?fm=jpg&w=2000",
        "width": 2000,
        "height": 382
      },
      "description": "Commercial illlustration",
      "alt": "Bus web banner graphic by Vickie Chan",
      "showInPortfolio": false
    },
    {
      "title": "68 Calendar",
      "year": "2011-09-23T00:00:00.000Z",
      "category": "commercial illustration",
      "srcImage": "https://www.datocms-assets.com/159/1506174135-2011_6_68printcalendarcomposite.jpg?fm=jpg&w=400",
      "mobileImage": {
        "src": "https://www.datocms-assets.com/159/1506174135-2011_6_68printcalendarcomposite.jpg?fm=jpg&w=800",
        "width": 800,
        "height": 1098
      },
      "desktopImage": {
        "src": "https://www.datocms-assets.com/159/1506174135-2011_6_68printcalendarcomposite.jpg?fm=jpg&w=2000",
        "width": 2000,
        "height": 2745
      },
      "description": "commercial illustration",
      "alt": "68 calendar graphic by Vickie Chan",
      "showInPortfolio": false
    },
    {
      "title": "68 Daily POP",
      "year": "2011-09-23T00:00:00.000Z",
      "category": "commercial illustration",
      "srcImage": "https://www.datocms-assets.com/159/1506174266-2011_5_68a1dailypopcomposite.jpg?fm=jpg&w=400",
      "mobileImage": {
        "src": "https://www.datocms-assets.com/159/1506174266-2011_5_68a1dailypopcomposite.jpg?fm=jpg&w=800",
        "width": 800,
        "height": 594
      },
      "desktopImage": {
        "src": "https://www.datocms-assets.com/159/1506174266-2011_5_68a1dailypopcomposite.jpg?fm=jpg&w=2000",
        "width": 2000,
        "height": 1485
      },
      "description": "Commercial illustration",
      "alt": "68 daily POP graphic by Vickie Chan",
      "showInPortfolio": false
    },
    {
      "title": "68 Launch Homepage",
      "year": "2011-09-29T00:00:00.000Z",
      "category": "commercial illustration",
      "srcImage": "https://www.datocms-assets.com/159/1506174344-2011_4_68mirafront.jpg?fm=jpg&w=400",
      "mobileImage": {
        "src": "https://www.datocms-assets.com/159/1506174344-2011_4_68mirafront.jpg?fm=jpg&w=800",
        "width": 800,
        "height": 542
      },
      "desktopImage": {
        "src": "https://www.datocms-assets.com/159/1506174344-2011_4_68mirafront.jpg?fm=jpg&w=2000",
        "width": 2000,
        "height": 1357
      },
      "description": "Commercial illustration",
      "alt": "68 launch homepage graphic by Vickie Chan",
      "showInPortfolio": false
    },
    {
      "title": "68 Launch Weekly Wow",
      "year": "2011-09-14T00:00:00.000Z",
      "category": "commercial illustration",
      "srcImage": "https://www.datocms-assets.com/159/1506174427-2011_3_68miraweeklywow.jpg?fm=jpg&w=400",
      "mobileImage": {
        "src": "https://www.datocms-assets.com/159/1506174427-2011_3_68miraweeklywow.jpg?fm=jpg&w=800",
        "width": 800,
        "height": 565
      },
      "desktopImage": {
        "src": "https://www.datocms-assets.com/159/1506174427-2011_3_68miraweeklywow.jpg?fm=jpg&w=2000",
        "width": 2000,
        "height": 1413
      },
      "description": "Commercial illustration",
      "alt": "68 Launch Weekly Wow graphic by Vickie Chan",
      "showInPortfolio": false
    },
    {
      "title": "68 Calendar Front",
      "year": "2011-09-23T00:00:00.000Z",
      "category": "commercial illustration",
      "srcImage": "https://www.datocms-assets.com/159/1506174482-2011_2_68miracalendarfront.jpg?fm=jpg&w=400",
      "mobileImage": {
        "src": "https://www.datocms-assets.com/159/1506174482-2011_2_68miracalendarfront.jpg?fm=jpg&w=800",
        "width": 800,
        "height": 612
      },
      "desktopImage": {
        "src": "https://www.datocms-assets.com/159/1506174482-2011_2_68miracalendarfront.jpg?fm=jpg&w=2000",
        "width": 2000,
        "height": 1530
      },
      "description": "Commercial illustration",
      "alt": "68 Calendar Front graphic by Vickie Chan",
      "showInPortfolio": false
    },
    {
      "title": "68 Bus Model",
      "year": "2011-09-13T00:00:00.000Z",
      "category": "commercial illustration",
      "srcImage": "https://www.datocms-assets.com/159/1506174552-2011_1a_68busmodel.jpg?fm=jpg&w=400",
      "mobileImage": {
        "src": "https://www.datocms-assets.com/159/1506174552-2011_1a_68busmodel.jpg?fm=jpg&w=800",
        "width": 800,
        "height": 502
      },
      "desktopImage": {
        "src": "https://www.datocms-assets.com/159/1506174552-2011_1a_68busmodel.jpg?fm=jpg&w=2000",
        "width": 2000,
        "height": 1256
      },
      "description": "Model of bus with commercial illlustration",
      "alt": "68 Bus Model – graphics by Vickie Chan",
      "showInPortfolio": false
    },
    {
      "title": "68 Bus",
      "year": "2011-09-23T00:00:00.000Z",
      "category": "commercial illustration",
      "srcImage": "https://www.datocms-assets.com/159/1506174596-2011_1_68bus.jpg?fm=jpg&w=400",
      "mobileImage": {
        "src": "https://www.datocms-assets.com/159/1506174596-2011_1_68bus.jpg?fm=jpg&w=800",
        "width": 800,
        "height": 531
      },
      "desktopImage": {
        "src": "https://www.datocms-assets.com/159/1506174596-2011_1_68bus.jpg?fm=jpg&w=2000",
        "width": 2000,
        "height": 1327
      },
      "description": "Commercial illustration",
      "alt": "68 Bus – graphics by Vickie Chan",
      "showInPortfolio": true
    },
    {
      "title": "Perhentian",
      "year": "2011-09-13T00:00:00.000Z",
      "category": "sketch",
      "srcImage": "https://www.datocms-assets.com/159/1506174662-perhentian.jpg?fm=jpg&w=400",
      "mobileImage": {
        "src": "https://www.datocms-assets.com/159/1506174662-perhentian.jpg?fm=jpg&w=800",
        "width": 800,
        "height": 584
      },
      "desktopImage": {
        "src": "https://www.datocms-assets.com/159/1506174662-perhentian.jpg?fm=jpg&w=2000",
        "width": 2000,
        "height": 1461
      },
      "description": "Ink sketch",
      "alt": "Perhentian ink sketch by Vickie Chan",
      "showInPortfolio": false
    },
    {
      "title": "A Letter to Elise",
      "year": "2011-09-14T00:00:00.000Z",
      "category": "painting",
      "srcImage": "https://www.datocms-assets.com/159/1506174715-alettertoelise_30_small.jpg?fm=jpg&w=400",
      "mobileImage": {
        "src": "https://www.datocms-assets.com/159/1506174715-alettertoelise_30_small.jpg?fm=jpg&w=800",
        "width": 800,
        "height": 794
      },
      "desktopImage": {
        "src": "https://www.datocms-assets.com/159/1506174715-alettertoelise_30_small.jpg?fm=jpg&w=2000",
        "width": 2000,
        "height": 1985
      },
      "description": "Mixed media on canvas",
      "alt": "A Letter to Elise painting by Vickie Chan",
      "showInPortfolio": false
    },
    {
      "title": "Mongkok Girls",
      "year": "2010-09-23T00:00:00.000Z",
      "category": "painting mixed-media",
      "srcImage": "https://www.datocms-assets.com/159/1506174797-mongkokgirlsfull.jpg?fm=jpg&w=400",
      "mobileImage": {
        "src": "https://www.datocms-assets.com/159/1506174797-mongkokgirlsfull.jpg?fm=jpg&w=800",
        "width": 800,
        "height": 1098
      },
      "desktopImage": {
        "src": "https://www.datocms-assets.com/159/1506174797-mongkokgirlsfull.jpg?fm=jpg&w=2000",
        "width": 2000,
        "height": 2747
      },
      "description": "Painting on vinyl record",
      "alt": "Mongkok Girls painting on vinyl by Vickie Chan",
      "showInPortfolio": false
    },
    {
      "title": "China Calling",
      "year": "2010-09-23T00:00:00.000Z",
      "category": "painting mixed-media",
      "srcImage": "https://www.datocms-assets.com/159/1506174883-chinacalling-fakefull.jpg?fm=jpg&w=400",
      "mobileImage": {
        "src": "https://www.datocms-assets.com/159/1506174883-chinacalling-fakefull.jpg?fm=jpg&w=800",
        "width": 800,
        "height": 1098
      },
      "desktopImage": {
        "src": "https://www.datocms-assets.com/159/1506174883-chinacalling-fakefull.jpg?fm=jpg&w=2000",
        "width": 2000,
        "height": 2747
      },
      "description": "Painting on vinyl record",
      "alt": "China Calling painting on vinyl by Vickie Chan",
      "showInPortfolio": false
    },
    {
      "title": "Hong Kong Garden",
      "year": "2010-09-28T00:00:00.000Z",
      "category": "painting mixed-media",
      "srcImage": "https://www.datocms-assets.com/159/1506174941-hongkongwhatgdnfull.jpg?fm=jpg&w=400",
      "mobileImage": {
        "src": "https://www.datocms-assets.com/159/1506174941-hongkongwhatgdnfull.jpg?fm=jpg&w=800",
        "width": 800,
        "height": 1098
      },
      "desktopImage": {
        "src": "https://www.datocms-assets.com/159/1506174941-hongkongwhatgdnfull.jpg?fm=jpg&w=2000",
        "width": 2000,
        "height": 2747
      },
      "description": "Painting on vinyl record",
      "alt": "Hong Kong Garden painting on vinyl by Vickie Chan",
      "showInPortfolio": false
    },
    {
      "title": "Haad Yuan",
      "year": "2010-09-23T00:00:00.000Z",
      "category": "sketch",
      "srcImage": "https://www.datocms-assets.com/159/1506174996-haadyuan.jpg?fm=jpg&w=400",
      "mobileImage": {
        "src": "https://www.datocms-assets.com/159/1506174996-haadyuan.jpg?fm=jpg&w=800",
        "width": 800,
        "height": 531
      },
      "desktopImage": {
        "src": "https://www.datocms-assets.com/159/1506174996-haadyuan.jpg?fm=jpg&w=2000",
        "width": 2000,
        "height": 1328
      },
      "description": "Ink sketch",
      "alt": "Haad Yuan ink sketch by Vickie Chan",
      "showInPortfolio": false
    },
    {
      "title": "Rhyme and Rhythm",
      "year": "2010-09-23T00:00:00.000Z",
      "category": "painting mixed-media",
      "srcImage": "https://www.datocms-assets.com/159/1506175050-rhymerhythm_21-5x29-5_small.jpg?fm=jpg&w=400",
      "mobileImage": {
        "src": "https://www.datocms-assets.com/159/1506175050-rhymerhythm_21-5x29-5_small.jpg?fm=jpg&w=800",
        "width": 800,
        "height": 1081
      },
      "desktopImage": {
        "src": "https://www.datocms-assets.com/159/1506175050-rhymerhythm_21-5x29-5_small.jpg?fm=jpg&w=2000",
        "width": 2000,
        "height": 2703
      },
      "description": "Mixed media on canvas",
      "alt": "Rhyme and Rhythm mixed media painting on canvas by Vickie Chan",
      "showInPortfolio": false
    },
    {
      "title": "Sailing on the Seven Seas",
      "year": "2010-09-23T00:00:00.000Z",
      "category": "painting mixed-media",
      "srcImage": "https://www.datocms-assets.com/159/1506175304-sailingonthesevenseas_20_small.jpg?fm=jpg&w=400",
      "mobileImage": {
        "src": "https://www.datocms-assets.com/159/1506175304-sailingonthesevenseas_20_small.jpg?fm=jpg&w=800",
        "width": 800,
        "height": 800
      },
      "desktopImage": {
        "src": "https://www.datocms-assets.com/159/1506175304-sailingonthesevenseas_20_small.jpg?fm=jpg&w=2000",
        "width": 2000,
        "height": 2000
      },
      "description": "Mixed media on canvas",
      "alt": "Sailing on the Seven Seas mixed media painting on canvas by Vickie Chan",
      "showInPortfolio": true
    },
    {
      "title": "Something Scary",
      "year": "2010-09-23T00:00:00.000Z",
      "category": "painting mixed-media",
      "srcImage": "https://www.datocms-assets.com/159/1506175380-somethingscarya_30_small.jpg?fm=jpg&w=400",
      "mobileImage": {
        "src": "https://www.datocms-assets.com/159/1506175380-somethingscarya_30_small.jpg?fm=jpg&w=800",
        "width": 800,
        "height": 775
      },
      "desktopImage": {
        "src": "https://www.datocms-assets.com/159/1506175380-somethingscarya_30_small.jpg?fm=jpg&w=2000",
        "width": 2000,
        "height": 1938
      },
      "description": "Mixed media on canvas",
      "alt": "Something Scary mixed media painting on canvas by Vickie Chan",
      "showInPortfolio": false
    },
    {
      "title": "Born to Lose",
      "year": "2010-09-23T00:00:00.000Z",
      "category": "painting",
      "srcImage": "https://www.datocms-assets.com/159/1506175445-borntolose_30_small.jpg?fm=jpg&w=400",
      "mobileImage": {
        "src": "https://www.datocms-assets.com/159/1506175445-borntolose_30_small.jpg?fm=jpg&w=800",
        "width": 800,
        "height": 794
      },
      "desktopImage": {
        "src": "https://www.datocms-assets.com/159/1506175445-borntolose_30_small.jpg?fm=jpg&w=2000",
        "width": 2000,
        "height": 1986
      },
      "description": "Mixed media on canvas",
      "alt": "Born to Lose mixed media painting on canvas by Vickie Chan",
      "showInPortfolio": false
    },
    {
      "title": "The Division (East and West)",
      "year": "2010-09-23T00:00:00.000Z",
      "category": "painting mixed-media",
      "srcImage": "https://www.datocms-assets.com/159/1506175497-thedivisionewfull.jpg?fm=jpg&w=400",
      "mobileImage": {
        "src": "https://www.datocms-assets.com/159/1506175497-thedivisionewfull.jpg?fm=jpg&w=800",
        "width": 800,
        "height": 1098
      },
      "desktopImage": {
        "src": "https://www.datocms-assets.com/159/1506175497-thedivisionewfull.jpg?fm=jpg&w=2000",
        "width": 2000,
        "height": 2747
      },
      "description": "Painting on vinyl record",
      "alt": "The Division (East and West) painting on vinyl by Vickie Chan",
      "showInPortfolio": false
    },
    {
      "title": "Such Great Heights (12 inch)",
      "year": "2009-09-23T00:00:00.000Z",
      "category": "painting mixed medium",
      "srcImage": "https://www.datocms-assets.com/159/1506175564-suchgreatheights_30_small.jpg?fm=jpg&w=400",
      "mobileImage": {
        "src": "https://www.datocms-assets.com/159/1506175564-suchgreatheights_30_small.jpg?fm=jpg&w=800",
        "width": 800,
        "height": 798
      },
      "desktopImage": {
        "src": "https://www.datocms-assets.com/159/1506175564-suchgreatheights_30_small.jpg?fm=jpg&w=2000",
        "width": 2000,
        "height": 1995
      },
      "description": "Mixed media on wood",
      "alt": "Such Great Heights (12) mixed media painting by Vickie Chan",
      "showInPortfolio": false
    },
    {
      "title": "Kokeshi Doll",
      "year": "2009-09-15T00:00:00.000Z",
      "category": "painting mixed-media",
      "srcImage": "https://www.datocms-assets.com/159/1506175672-kokeshi_12_small.jpg?fm=jpg&w=400",
      "mobileImage": {
        "src": "https://www.datocms-assets.com/159/1506175672-kokeshi_12_small.jpg?fm=jpg&w=800",
        "width": 800,
        "height": 800
      },
      "desktopImage": {
        "src": "https://www.datocms-assets.com/159/1506175672-kokeshi_12_small.jpg?fm=jpg&w=2000",
        "width": 2000,
        "height": 2000
      },
      "description": "Acrylic and goldleaf on wood",
      "alt": "Kokeshi doll mixed media painting by Vickie Chan",
      "showInPortfolio": false
    },
    {
      "title": "Gville Yard",
      "year": "2008-09-23T00:00:00.000Z",
      "category": "sketch",
      "srcImage": "https://www.datocms-assets.com/159/1506175774-gvilleyard.jpg?fm=jpg&w=400",
      "mobileImage": {
        "src": "https://www.datocms-assets.com/159/1506175774-gvilleyard.jpg?fm=jpg&w=800",
        "width": 800,
        "height": 866
      },
      "desktopImage": {
        "src": "https://www.datocms-assets.com/159/1506175774-gvilleyard.jpg?fm=jpg&w=2000",
        "width": 2000,
        "height": 2166
      },
      "description": "Ink sketch",
      "alt": "Gville Yard ink sketch by Vickie Chan",
      "showInPortfolio": false
    },
    {
      "title": "Untitled (Should I Stay)",
      "year": "2008-09-23T00:00:00.000Z",
      "category": "painting mixed-media",
      "srcImage": "https://www.datocms-assets.com/159/1506175840-untitled_shouldistay_30_small.jpg?fm=jpg&w=400",
      "mobileImage": {
        "src": "https://www.datocms-assets.com/159/1506175840-untitled_shouldistay_30_small.jpg?fm=jpg&w=800",
        "width": 800,
        "height": 798
      },
      "desktopImage": {
        "src": "https://www.datocms-assets.com/159/1506175840-untitled_shouldistay_30_small.jpg?fm=jpg&w=2000",
        "width": 2000,
        "height": 1995
      },
      "description": "Mixed media on canvas",
      "alt": "Untitled (Should I Stay) mixed media painting on canvas by Vickie Chan",
      "showInPortfolio": false
    },
    {
      "title": "Sever",
      "year": "2008-09-23T00:00:00.000Z",
      "category": "painting mixed-media",
      "srcImage": "https://www.datocms-assets.com/159/1506175923-sever_20_small.jpg?fm=jpg&w=400",
      "mobileImage": {
        "src": "https://www.datocms-assets.com/159/1506175923-sever_20_small.jpg?fm=jpg&w=800",
        "width": 800,
        "height": 798
      },
      "desktopImage": {
        "src": "https://www.datocms-assets.com/159/1506175923-sever_20_small.jpg?fm=jpg&w=2000",
        "width": 2000,
        "height": 1995
      },
      "description": "Mixed media on canvas",
      "alt": "Sever mixed media painting on canvas by Vickie Chan",
      "showInPortfolio": false
    },
    {
      "title": "War All The Time",
      "year": "2008-09-23T00:00:00.000Z",
      "category": "painting mixed-media",
      "srcImage": "https://www.datocms-assets.com/159/1506176069-warallthetime_20_small.jpg?fm=jpg&w=400",
      "mobileImage": {
        "src": "https://www.datocms-assets.com/159/1506176069-warallthetime_20_small.jpg?fm=jpg&w=800",
        "width": 800,
        "height": 800
      },
      "desktopImage": {
        "src": "https://www.datocms-assets.com/159/1506176069-warallthetime_20_small.jpg?fm=jpg&w=2000",
        "width": 2000,
        "height": 2002
      },
      "description": "War All The Time mixed media painting on canvas by Vickie Chan",
      "alt": "War All The Time mixed media painting on canvas by Vickie Chan",
      "showInPortfolio": false
    },
    {
      "title": "Butterfly Heart",
      "year": "2007-09-23T00:00:00.000Z",
      "category": "illustration",
      "srcImage": "https://www.datocms-assets.com/159/1506176139-butterflyheart_12_small.jpg?fm=jpg&w=400",
      "mobileImage": {
        "src": "https://www.datocms-assets.com/159/1506176139-butterflyheart_12_small.jpg?fm=jpg&w=800",
        "width": 800,
        "height": 803
      },
      "desktopImage": {
        "src": "https://www.datocms-assets.com/159/1506176139-butterflyheart_12_small.jpg?fm=jpg&w=2000",
        "width": 2000,
        "height": 2007
      },
      "description": "Ink and paint on wood",
      "alt": "Butterfly Heart ink and paint on wood by Vickie Chan",
      "showInPortfolio": true
    },
    {
      "title": "Road to Nowhere",
      "year": "2007-09-23T00:00:00.000Z",
      "category": "painting mixed-media",
      "srcImage": "https://www.datocms-assets.com/159/1506176199-roadtonowhere_12_small.jpg?fm=jpg&w=400",
      "mobileImage": {
        "src": "https://www.datocms-assets.com/159/1506176199-roadtonowhere_12_small.jpg?fm=jpg&w=800",
        "width": 800,
        "height": 801
      },
      "desktopImage": {
        "src": "https://www.datocms-assets.com/159/1506176199-roadtonowhere_12_small.jpg?fm=jpg&w=2000",
        "width": 2000,
        "height": 2003
      },
      "description": "Mixed media on canvas",
      "alt": "Road to Nowhere mixed media painting on canvas by Vickie Chan",
      "showInPortfolio": false
    },
    {
      "title": "Round the Corner",
      "year": "2007-09-26T00:00:00.000Z",
      "category": "painting mixed-media",
      "srcImage": "https://www.datocms-assets.com/159/1506176267-roundthecorner_12_small.jpg?fm=jpg&w=400",
      "mobileImage": {
        "src": "https://www.datocms-assets.com/159/1506176267-roundthecorner_12_small.jpg?fm=jpg&w=800",
        "width": 800,
        "height": 805
      },
      "desktopImage": {
        "src": "https://www.datocms-assets.com/159/1506176267-roundthecorner_12_small.jpg?fm=jpg&w=2000",
        "width": 2000,
        "height": 2013
      },
      "description": "Mixed media on canvas",
      "alt": "Round the Corner mixed media painting on canvas by Vickie Chan",
      "showInPortfolio": false
    },
    {
      "title": "Lovecats",
      "year": "2007-09-23T00:00:00.000Z",
      "category": "painting mixed-media",
      "srcImage": "https://www.datocms-assets.com/159/1506176333-lovecats_10_small.jpg?fm=jpg&w=400",
      "mobileImage": {
        "src": "https://www.datocms-assets.com/159/1506176333-lovecats_10_small.jpg?fm=jpg&w=800",
        "width": 800,
        "height": 785
      },
      "desktopImage": {
        "src": "https://www.datocms-assets.com/159/1506176333-lovecats_10_small.jpg?fm=jpg&w=2000",
        "width": 2000,
        "height": 1964
      },
      "description": "Mixed media on canvas",
      "alt": "Lovecats mixed media painting on canvas by Vickie Chan",
      "showInPortfolio": false
    },
    {
      "title": "Untitled (Tigger)",
      "year": "2007-09-25T00:00:00.000Z",
      "category": "painting mixed-media",
      "srcImage": "https://www.datocms-assets.com/159/1506176399-tig_8_small.jpg?fm=jpg&w=400",
      "mobileImage": {
        "src": "https://www.datocms-assets.com/159/1506176399-tig_8_small.jpg?fm=jpg&w=800",
        "width": 800,
        "height": 793
      },
      "desktopImage": {
        "src": "https://www.datocms-assets.com/159/1506176399-tig_8_small.jpg?fm=jpg&w=2000",
        "width": 2000,
        "height": 1984
      },
      "description": "Painting on canvas",
      "alt": "Untitled (Tigger) painting on canvas by Vickie Chan",
      "showInPortfolio": false
    },
    {
      "title": "India",
      "year": "2009-09-23T00:00:00.000Z",
      "category": "sketch",
      "srcImage": "https://www.datocms-assets.com/159/1506176472-india.jpg?fm=jpg&w=400",
      "mobileImage": {
        "src": "https://www.datocms-assets.com/159/1506176472-india.jpg?fm=jpg&w=800",
        "width": 800,
        "height": 864
      },
      "desktopImage": {
        "src": "https://www.datocms-assets.com/159/1506176472-india.jpg?fm=jpg&w=2000",
        "width": 2000,
        "height": 2160
      },
      "description": "Ink sketch",
      "alt": "India ink sketch by Vickie Chan",
      "showInPortfolio": false
    },
    {
      "title": "Ship Song",
      "year": "2006-09-19T00:00:00.000Z",
      "category": "painting mixed-media",
      "srcImage": "https://www.datocms-assets.com/159/1506176536-shipsong_30_small.jpg?fm=jpg&w=400",
      "mobileImage": {
        "src": "https://www.datocms-assets.com/159/1506176536-shipsong_30_small.jpg?fm=jpg&w=800",
        "width": 800,
        "height": 806
      },
      "desktopImage": {
        "src": "https://www.datocms-assets.com/159/1506176536-shipsong_30_small.jpg?fm=jpg&w=2000",
        "width": 2000,
        "height": 2016
      },
      "description": "Mixed media on canvas",
      "alt": "Ship Song mixed media painting on canvas by Vickie Chan",
      "showInPortfolio": false
    },
    {
      "title": "Three Summers Strong",
      "year": "2006-09-23T00:00:00.000Z",
      "category": "painting",
      "srcImage": "https://www.datocms-assets.com/159/1506177716-threesummersstrong_30_small.jpg?fm=jpg&w=400",
      "mobileImage": {
        "src": "https://www.datocms-assets.com/159/1506177716-threesummersstrong_30_small.jpg?fm=jpg&w=800",
        "width": 800,
        "height": 803
      },
      "desktopImage": {
        "src": "https://www.datocms-assets.com/159/1506177716-threesummersstrong_30_small.jpg?fm=jpg&w=2000",
        "width": 2000,
        "height": 2008
      },
      "description": "Mixed media on canvas",
      "alt": "Three Summers Strong mixed media painting on canvas by Vickie Chan",
      "showInPortfolio": false
    },
    {
      "title": "True Colo(u)rs",
      "year": "2006-09-13T00:00:00.000Z",
      "category": "painting mixed-media",
      "srcImage": "https://www.datocms-assets.com/159/1506177790-truecolors_30_small.jpg?fm=jpg&w=400",
      "mobileImage": {
        "src": "https://www.datocms-assets.com/159/1506177790-truecolors_30_small.jpg?fm=jpg&w=800",
        "width": 800,
        "height": 800
      },
      "desktopImage": {
        "src": "https://www.datocms-assets.com/159/1506177790-truecolors_30_small.jpg?fm=jpg&w=2000",
        "width": 2000,
        "height": 2000
      },
      "description": "Mixed media on canvas",
      "alt": "True Colo(u)rs mixed media painting on canvas by Vickie Chan",
      "showInPortfolio": false
    },
    {
      "title": "It's Hard to Know",
      "year": "2006-09-23T00:00:00.000Z",
      "category": "painting mixed-media",
      "srcImage": "https://www.datocms-assets.com/159/1506177851-itshardtoknow_20_small.jpg?fm=jpg&w=400",
      "mobileImage": {
        "src": "https://www.datocms-assets.com/159/1506177851-itshardtoknow_20_small.jpg?fm=jpg&w=800",
        "width": 800,
        "height": 809
      },
      "desktopImage": {
        "src": "https://www.datocms-assets.com/159/1506177851-itshardtoknow_20_small.jpg?fm=jpg&w=2000",
        "width": 2000,
        "height": 2022
      },
      "description": "Mixed media on canvas",
      "alt": "It's Hard to Know mixed media painting on canvas by Vickie Chan",
      "showInPortfolio": false
    },
    {
      "title": "Colver Road",
      "year": "2005-09-23T00:00:00.000Z",
      "category": "sketch",
      "srcImage": "https://www.datocms-assets.com/159/1506177914-colver.jpg?fm=jpg&w=400",
      "mobileImage": {
        "src": "https://www.datocms-assets.com/159/1506177914-colver.jpg?fm=jpg&w=800",
        "width": 800,
        "height": 890
      },
      "desktopImage": {
        "src": "https://www.datocms-assets.com/159/1506177914-colver.jpg?fm=jpg&w=2000",
        "width": 2000,
        "height": 2226
      },
      "description": "Ink sketch",
      "alt": "Colver Road ink sketch by Vickie Chan",
      "showInPortfolio": false
    },
    {
      "title": "Stranger to Bluewater",
      "year": "2005-09-23T00:00:00.000Z",
      "category": "painting",
      "srcImage": "https://www.datocms-assets.com/159/1506177976-strangertobluewater_20_small.jpg?fm=jpg&w=400",
      "mobileImage": {
        "src": "https://www.datocms-assets.com/159/1506177976-strangertobluewater_20_small.jpg?fm=jpg&w=800",
        "width": 800,
        "height": 805
      },
      "desktopImage": {
        "src": "https://www.datocms-assets.com/159/1506177976-strangertobluewater_20_small.jpg?fm=jpg&w=2000",
        "width": 2000,
        "height": 2012
      },
      "description": "Acrylic on canvas",
      "alt": "Stranger to Bluewater painting on canvas by Vickie Chan",
      "showInPortfolio": false
    },
    {
      "title": "Wish You Were Here",
      "year": "2004-09-23T00:00:00.000Z",
      "category": "painting mixed-media",
      "srcImage": "https://www.datocms-assets.com/159/1506178034-wishyouwerehere_20_small.jpg?fm=jpg&w=400",
      "mobileImage": {
        "src": "https://www.datocms-assets.com/159/1506178034-wishyouwerehere_20_small.jpg?fm=jpg&w=800",
        "width": 800,
        "height": 816
      },
      "desktopImage": {
        "src": "https://www.datocms-assets.com/159/1506178034-wishyouwerehere_20_small.jpg?fm=jpg&w=2000",
        "width": 2000,
        "height": 2041
      },
      "description": "Mixed media on canvas",
      "alt": "Wish You Were Here painting by Vickie Chan",
      "showInPortfolio": false
    },
    {
      "title": "The Days Run Away",
      "year": "2004-09-23T00:00:00.000Z",
      "category": "painting mixed-media",
      "srcImage": "https://www.datocms-assets.com/159/1506178101-thedaysrunaway_20_small.jpg?fm=jpg&w=400",
      "mobileImage": {
        "src": "https://www.datocms-assets.com/159/1506178101-thedaysrunaway_20_small.jpg?fm=jpg&w=800",
        "width": 800,
        "height": 811
      },
      "desktopImage": {
        "src": "https://www.datocms-assets.com/159/1506178101-thedaysrunaway_20_small.jpg?fm=jpg&w=2000",
        "width": 2000,
        "height": 2029
      },
      "description": "Mixed media on canvas",
      "alt": "The Days Run Away mixed media painting on canvas by Vickie Chan",
      "showInPortfolio": false
    },
    {
      "title": "Germany Tour",
      "year": "2003-09-23T00:00:00.000Z",
      "category": "sketch",
      "srcImage": "https://www.datocms-assets.com/159/1506178197-germany_tour.jpg?fm=jpg&w=400",
      "mobileImage": {
        "src": "https://www.datocms-assets.com/159/1506178197-germany_tour.jpg?fm=jpg&w=800",
        "width": 800,
        "height": 913
      },
      "desktopImage": {
        "src": "https://www.datocms-assets.com/159/1506178197-germany_tour.jpg?fm=jpg&w=2000",
        "width": 2000,
        "height": 2283
      },
      "description": "Ink sketch",
      "alt": "Germany Tour ink sketch by Vickie Chan",
      "showInPortfolio": false
    },
    {
      "title": "Pine Cottage",
      "year": "2003-09-22T00:00:00.000Z",
      "category": "screenprint mixed-media",
      "srcImage": "https://www.datocms-assets.com/159/1506178248-pinecott_10_small.jpg?fm=jpg&w=400",
      "mobileImage": {
        "src": "https://www.datocms-assets.com/159/1506178248-pinecott_10_small.jpg?fm=jpg&w=800",
        "width": 800,
        "height": 812
      },
      "desktopImage": {
        "src": "https://www.datocms-assets.com/159/1506178248-pinecott_10_small.jpg?fm=jpg&w=2000",
        "width": 2000,
        "height": 2032
      },
      "description": "Embellished screenprint",
      "alt": "Pine Cottage mixed media screenprint by Vickie Chan",
      "showInPortfolio": false
    },
    {
      "title": "Sky Station",
      "year": "2003-09-23T00:00:00.000Z",
      "category": "screenprint mixed-media",
      "srcImage": "https://www.datocms-assets.com/159/1506178307-skystation_10_small.jpg?fm=jpg&w=400",
      "mobileImage": {
        "src": "https://www.datocms-assets.com/159/1506178307-skystation_10_small.jpg?fm=jpg&w=800",
        "width": 800,
        "height": 794
      },
      "desktopImage": {
        "src": "https://www.datocms-assets.com/159/1506178307-skystation_10_small.jpg?fm=jpg&w=2000",
        "width": 2000,
        "height": 1985
      },
      "description": "Embellished screenprint",
      "alt": "Sky Station mixed media screenprint by Vickie Chan",
      "showInPortfolio": false
    },
    {
      "title": "St Saviour's",
      "year": "2003-09-30T00:00:00.000Z",
      "category": "screenprint mixed-media",
      "srcImage": "https://www.datocms-assets.com/159/1506178382-stsav_10_small.jpg?fm=jpg&w=400",
      "mobileImage": {
        "src": "https://www.datocms-assets.com/159/1506178382-stsav_10_small.jpg?fm=jpg&w=800",
        "width": 800,
        "height": 841
      },
      "desktopImage": {
        "src": "https://www.datocms-assets.com/159/1506178382-stsav_10_small.jpg?fm=jpg&w=2000",
        "width": 2000,
        "height": 2103
      },
      "description": "Embellished screenprint",
      "alt": "St Saviour's mixed media screenprint by Vickie Chan",
      "showInPortfolio": false
    },
    {
      "title": "Leicester Shop",
      "year": "2003-09-23T00:00:00.000Z",
      "category": "screenprint mixed-media",
      "srcImage": "https://www.datocms-assets.com/159/1506178465-leicestershop_10_small.jpg?fm=jpg&w=400",
      "mobileImage": {
        "src": "https://www.datocms-assets.com/159/1506178465-leicestershop_10_small.jpg?fm=jpg&w=800",
        "width": 800,
        "height": 800
      },
      "desktopImage": {
        "src": "https://www.datocms-assets.com/159/1506178465-leicestershop_10_small.jpg?fm=jpg&w=2000",
        "width": 2000,
        "height": 2000
      },
      "description": "Embellished screenprint",
      "alt": "Leicester Shop mixed media screenprint by Vickie Chan",
      "showInPortfolio": false
    },
    {
      "title": "A Mess",
      "year": "2003-09-23T00:00:00.000Z",
      "category": "painting mixed-media",
      "srcImage": "https://www.datocms-assets.com/159/1506178530-a-mess_8_small.jpg?fm=jpg&w=400",
      "mobileImage": {
        "src": "https://www.datocms-assets.com/159/1506178530-a-mess_8_small.jpg?fm=jpg&w=800",
        "width": 800,
        "height": 793
      },
      "desktopImage": {
        "src": "https://www.datocms-assets.com/159/1506178530-a-mess_8_small.jpg?fm=jpg&w=2000",
        "width": 2000,
        "height": 1983
      },
      "description": "A Mess mixed media painting on canvas by Vickie Chan",
      "alt": "A Mess mixed media painting on canvas by Vickie Chan",
      "showInPortfolio": false
    },
    {
      "title": "Fused",
      "year": "2003-09-23T00:00:00.000Z",
      "category": "painting mixed-media",
      "srcImage": "https://www.datocms-assets.com/159/1506178593-fused_8_small.jpg?fm=jpg&w=400",
      "mobileImage": {
        "src": "https://www.datocms-assets.com/159/1506178593-fused_8_small.jpg?fm=jpg&w=800",
        "width": 800,
        "height": 815
      },
      "desktopImage": {
        "src": "https://www.datocms-assets.com/159/1506178593-fused_8_small.jpg?fm=jpg&w=2000",
        "width": 2000,
        "height": 2039
      },
      "description": "Mixed media on canvas",
      "alt": "Fused mixed media painting on canvas by Vickie Chan",
      "showInPortfolio": false
    },
    {
      "title": "Left and Leaving",
      "year": "2003-09-11T00:00:00.000Z",
      "category": "painting mixed-media",
      "srcImage": "https://www.datocms-assets.com/159/1506178658-leftandleaving_8_small.jpg?fm=jpg&w=400",
      "mobileImage": {
        "src": "https://www.datocms-assets.com/159/1506178658-leftandleaving_8_small.jpg?fm=jpg&w=800",
        "width": 800,
        "height": 820
      },
      "desktopImage": {
        "src": "https://www.datocms-assets.com/159/1506178658-leftandleaving_8_small.jpg?fm=jpg&w=2000",
        "width": 2000,
        "height": 2050
      },
      "description": "Mixed media on canvas",
      "alt": "Left and Leaving mixed media painting on canvas by Vickie Chan",
      "showInPortfolio": false
    },
    {
      "title": "Me, Myself and I",
      "year": "2002-09-30T00:00:00.000Z",
      "category": "screenprint",
      "srcImage": "https://www.datocms-assets.com/159/1506178722-memyselfi_tri-print-wht.jpg?fm=jpg&w=400",
      "mobileImage": {
        "src": "https://www.datocms-assets.com/159/1506178722-memyselfi_tri-print-wht.jpg?fm=jpg&w=800",
        "width": 800,
        "height": 589
      },
      "desktopImage": {
        "src": "https://www.datocms-assets.com/159/1506178722-memyselfi_tri-print-wht.jpg?fm=jpg&w=2000",
        "width": 2000,
        "height": 1474
      },
      "description": "Screenprint",
      "alt": "Me, Myself and I screenprint by Vickie Chan",
      "showInPortfolio": false
    },
    {
      "title": "雀仔",
      "year": "2002-09-23T00:00:00.000Z",
      "category": "sketch",
      "srcImage": "https://www.datocms-assets.com/159/1506179078-birds.jpg?fm=jpg&w=400",
      "mobileImage": {
        "src": "https://www.datocms-assets.com/159/1506179078-birds.jpg?fm=jpg&w=800",
        "width": 800,
        "height": 826
      },
      "desktopImage": {
        "src": "https://www.datocms-assets.com/159/1506179078-birds.jpg?fm=jpg&w=2000",
        "width": 2000,
        "height": 2066
      },
      "description": "Ink sketch",
      "alt": "雀仔 ink sketch by Vickie Chan",
      "showInPortfolio": false
    },
    {
      "title": "Chinatown Window, SF",
      "year": "2002-09-23T00:00:00.000Z",
      "category": "screenprint illustration commercial",
      "srcImage": "https://www.datocms-assets.com/159/1506179161-chinatownwindow_print.jpg?fm=jpg&w=400",
      "mobileImage": {
        "src": "https://www.datocms-assets.com/159/1506179161-chinatownwindow_print.jpg?fm=jpg&w=800",
        "width": 800,
        "height": 560
      },
      "desktopImage": {
        "src": "https://www.datocms-assets.com/159/1506179161-chinatownwindow_print.jpg?fm=jpg&w=2000",
        "width": 2000,
        "height": 1402
      },
      "description": "Screenprint",
      "alt": "Chinatown Window, SF screenprint by Vickie Chan",
      "showInPortfolio": false
    },
    {
      "title": "China Rooftops",
      "year": "2002-09-23T00:00:00.000Z",
      "category": "sketch",
      "srcImage": "https://www.datocms-assets.com/159/1506179221-china.jpg?fm=jpg&w=400",
      "mobileImage": {
        "src": "https://www.datocms-assets.com/159/1506179221-china.jpg?fm=jpg&w=800",
        "width": 800,
        "height": 876
      },
      "desktopImage": {
        "src": "https://www.datocms-assets.com/159/1506179221-china.jpg?fm=jpg&w=2000",
        "width": 2000,
        "height": 2191
      },
      "description": "ink sketch1",
      "alt": "China Rooftops ink sketch by Vickie Chan",
      "showInPortfolio": false
    },
    {
      "title": "Birdcage",
      "year": "2002-09-17T00:00:00.000Z",
      "category": "sketch",
      "srcImage": "https://www.datocms-assets.com/159/1506179270-birdcage.jpg?fm=jpg&w=400",
      "mobileImage": {
        "src": "https://www.datocms-assets.com/159/1506179270-birdcage.jpg?fm=jpg&w=800",
        "width": 800,
        "height": 873
      },
      "desktopImage": {
        "src": "https://www.datocms-assets.com/159/1506179270-birdcage.jpg?fm=jpg&w=2000",
        "width": 2000,
        "height": 2183
      },
      "description": "Ink sketch",
      "alt": "Birdcage ink sketch by Vickie Chan",
      "showInPortfolio": false
    },
    {
      "title": "Swimming Pool",
      "year": "2002-09-23T00:00:00.000Z",
      "category": "mixed-media",
      "srcImage": "https://www.datocms-assets.com/159/1506179361-swimmingpool_8.jpg?fm=jpg&w=400",
      "mobileImage": {
        "src": "https://www.datocms-assets.com/159/1506179361-swimmingpool_8.jpg?fm=jpg&w=800",
        "width": 800,
        "height": 836
      },
      "desktopImage": {
        "src": "https://www.datocms-assets.com/159/1506179361-swimmingpool_8.jpg?fm=jpg&w=2000",
        "width": 2000,
        "height": 2091
      },
      "description": "Mixed media on canvas",
      "alt": "Swimming Pool mixed media on canvas by Vickie Chan",
      "showInPortfolio": true
    },
    {
      "title": "Mahjong",
      "year": "2002-09-23T00:00:00.000Z",
      "category": "screenprint mixed-media",
      "srcImage": "https://www.datocms-assets.com/159/1506179448-2002_mahjong_sequin_colour_10_small.jpg?fm=jpg&w=400",
      "mobileImage": {
        "src": "https://www.datocms-assets.com/159/1506179448-2002_mahjong_sequin_colour_10_small.jpg?fm=jpg&w=800",
        "width": 800,
        "height": 815
      },
      "desktopImage": {
        "src": "https://www.datocms-assets.com/159/1506179448-2002_mahjong_sequin_colour_10_small.jpg?fm=jpg&w=2000",
        "width": 2000,
        "height": 2038
      },
      "description": "Embellished mixed media screenprint",
      "alt": "Mahjong mixed media screenprint by Vickie Chan",
      "showInPortfolio": false
    },
    {
      "title": "Tram Boy",
      "year": "2002-09-23T00:00:00.000Z",
      "category": "screenprint mixed-media",
      "srcImage": "https://www.datocms-assets.com/159/1506179505-2002_tramboy_sequin_colour_10_small.jpg?fm=jpg&w=400",
      "mobileImage": {
        "src": "https://www.datocms-assets.com/159/1506179505-2002_tramboy_sequin_colour_10_small.jpg?fm=jpg&w=800",
        "width": 800,
        "height": 816
      },
      "desktopImage": {
        "src": "https://www.datocms-assets.com/159/1506179505-2002_tramboy_sequin_colour_10_small.jpg?fm=jpg&w=2000",
        "width": 2000,
        "height": 2042
      },
      "description": "Embellished mixed media screenprint",
      "alt": "Tram Boy mixed media screenprint by Vickie Chan",
      "showInPortfolio": false
    },
    {
      "title": "General Kwan",
      "year": "2002-09-23T00:00:00.000Z",
      "category": "screenprint mixed-media",
      "srcImage": "https://www.datocms-assets.com/159/1506179602-2002_generalkwan_sequin_10_small.jpg?fm=jpg&w=400",
      "mobileImage": {
        "src": "https://www.datocms-assets.com/159/1506179602-2002_generalkwan_sequin_10_small.jpg?fm=jpg&w=800",
        "width": 800,
        "height": 799
      },
      "desktopImage": {
        "src": "https://www.datocms-assets.com/159/1506179602-2002_generalkwan_sequin_10_small.jpg?fm=jpg&w=2000",
        "width": 2000,
        "height": 2000
      },
      "description": "Embellished mixed media screenprint",
      "alt": "General Kwan mixed media screenprint by Vickie Chan",
      "showInPortfolio": false
    },
    {
      "title": "Tin Hau",
      "year": "2002-09-23T00:00:00.000Z",
      "category": "screenprint mixed-media",
      "srcImage": "https://www.datocms-assets.com/159/1506179689-2002_tinhau_colour_sequin_10_small.jpg?fm=jpg&w=400",
      "mobileImage": {
        "src": "https://www.datocms-assets.com/159/1506179689-2002_tinhau_colour_sequin_10_small.jpg?fm=jpg&w=800",
        "width": 800,
        "height": 798
      },
      "desktopImage": {
        "src": "https://www.datocms-assets.com/159/1506179689-2002_tinhau_colour_sequin_10_small.jpg?fm=jpg&w=2000",
        "width": 2000,
        "height": 1995
      },
      "description": "Embellished mixed media screenprint",
      "alt": "Tin Hau mixed media screenprint by Vickie Chan",
      "showInPortfolio": false
    },
    {
      "title": "Market",
      "year": "2002-09-23T00:00:00.000Z",
      "category": "screenprint mixed-media",
      "srcImage": "https://www.datocms-assets.com/159/1506179783-2002_market_colour_sequin_10_small.jpg?fm=jpg&w=400",
      "mobileImage": {
        "src": "https://www.datocms-assets.com/159/1506179783-2002_market_colour_sequin_10_small.jpg?fm=jpg&w=800",
        "width": 800,
        "height": 800
      },
      "desktopImage": {
        "src": "https://www.datocms-assets.com/159/1506179783-2002_market_colour_sequin_10_small.jpg?fm=jpg&w=2000",
        "width": 2000,
        "height": 2000
      },
      "description": "Embellished mixed media screenprint",
      "alt": "Market mixed media screenprint by Vickie Chan",
      "showInPortfolio": false
    },
    {
      "title": "Everyone I See is You",
      "year": "2001-09-23T00:00:00.000Z",
      "category": "painting mixed-media",
      "srcImage": "https://www.datocms-assets.com/159/1506179864-everyoneiseeisyou.jpg?fm=jpg&w=400",
      "mobileImage": {
        "src": "https://www.datocms-assets.com/159/1506179864-everyoneiseeisyou.jpg?fm=jpg&w=800",
        "width": 800,
        "height": 800
      },
      "desktopImage": {
        "src": "https://www.datocms-assets.com/159/1506179864-everyoneiseeisyou.jpg?fm=jpg&w=2000",
        "width": 2000,
        "height": 2000
      },
      "description": "Mixed media on canvas",
      "alt": "Everyone I See is You mixed media painting on canvas by Vickie Chan",
      "showInPortfolio": true
    }
  ]
}